odoo/addons/product_print_category/README.rst
odoo/addons/product_print_category/__init__.py
odoo/addons/product_print_category/__manifest__.py
odoo/addons/product_print_category/data/report_paperformat.xml
odoo/addons/product_print_category/demo/product_print_category.xml
odoo/addons/product_print_category/demo/product_print_category_rule.xml
odoo/addons/product_print_category/demo/product_product.xml
odoo/addons/product_print_category/demo/qweb_template.xml
odoo/addons/product_print_category/demo/res_groups.xml
odoo/addons/product_print_category/i18n/es.po
odoo/addons/product_print_category/i18n/fr.po
odoo/addons/product_print_category/i18n/it.po
odoo/addons/product_print_category/i18n/product_print_category.pot
odoo/addons/product_print_category/models/__init__.py
odoo/addons/product_print_category/models/product_print_category.py
odoo/addons/product_print_category/models/product_print_category_mixin.py
odoo/addons/product_print_category/models/product_print_category_rule.py
odoo/addons/product_print_category/models/product_product.py
odoo/addons/product_print_category/models/product_template.py
odoo/addons/product_print_category/readme/CONFIGURE.md
odoo/addons/product_print_category/readme/CONTRIBUTORS.md
odoo/addons/product_print_category/readme/DESCRIPTION.md
odoo/addons/product_print_category/readme/USAGE.md
odoo/addons/product_print_category/report/__init__.py
odoo/addons/product_print_category/report/ir_actions_report.xml
odoo/addons/product_print_category/report/report_pricetag.py
odoo/addons/product_print_category/report/report_pricetag.xml
odoo/addons/product_print_category/security/ir.model.access.csv
odoo/addons/product_print_category/security/ir_rule.xml
odoo/addons/product_print_category/security/res_groups.xml
odoo/addons/product_print_category/static/description/icon.png
odoo/addons/product_print_category/static/description/index.html
odoo/addons/product_print_category/static/description/index.png
odoo_addon_product_print_category-18.0.1.0.1.dist-info/METADATA
odoo_addon_product_print_category-18.0.1.0.1.dist-info/WHEEL
odoo_addon_product_print_category-18.0.1.0.1.dist-info/top_level.txt
odoo_addon_product_print_category-18.0.1.0.1.dist-info/RECORD
